fies/__init__.py
fies/test.py
fies-1.6.0.dist-info/METADATA
fies-1.6.0.dist-info/WHEEL
fies-1.6.0.dist-info/top_level.txt
fies-1.6.0.dist-info/RECORD
