Metadata-Version: 2.1
Name: fies
Version: 1.6.0
Summary: A tool to easily read and write json files, pickle files, binary files, csv files and plain text files.
Home-page: https://github.co.jp/
Author: le_lattelle
Author-email: g.tiger.ml@gmail.com
License: CC0 v1.0
Classifier: Programming Language :: Python :: 3
Classifier: Topic :: Software Development :: Libraries
Classifier: License :: CC0 1.0 Universal (CC0 1.0) Public Domain Dedication
Requires-Dist: relpath
Requires-Dist: ezpip
Requires-Dist: sout
